miraculous/__init__.py
miraculous-1.8.5.dist-info/METADATA
miraculous-1.8.5.dist-info/WHEEL
miraculous-1.8.5.dist-info/top_level.txt
miraculous-1.8.5.dist-info/RECORD
