Metadata-Version: 2.1
Name: miraculous
Version: 1.8.5
Summary: A discord.py bot ready to use!
Home-page: https://github.com/I-make-python-module-and-bots-stuff/D.py-M
Author: Rukchad Wongprayoon
Author-email: mooping3roblox@gmail.com
License: MIT
Keywords: Tools
Platform: UNKNOWN
Requires-Dist: discord
Requires-Dist: discord-ext-alternatives
Requires-Dist: async-timeout
Requires-Dist: youtube-dl
Requires-Dist: flask
Requires-Dist: pynacl
